setup.py
django_rdfalchemy.egg-info/PKG-INFO
django_rdfalchemy.egg-info/SOURCES.txt
django_rdfalchemy.egg-info/dependency_links.txt
django_rdfalchemy.egg-info/not-zip-safe
django_rdfalchemy.egg-info/top_level.txt
djrdf/__init__.py
djrdf/forms.py
djrdf/models.py
djrdf/repository.py