Metadata-Version: 1.0
Name: django-rdfalchemy
Version: 0.0.1
Summary: Extension to mix Django ORM and RDFAlchemy models
Home-page: https://github.com/quinode/django-rdfalchemy/
Author: Cooperative Quinode
Author-email: claude.huchet@quinode.fr
License: BSD
Download-URL: https://github.com/quinode/django-rdfalchemy/tarball/master
Platform: UNKNOWN
Classifier: Development Status :: 4 - Beta
Classifier: Environment :: Web Environment
Classifier: Intended Audience :: Developers
Classifier: License :: OSI Approved :: BSD License
Classifier: Operating System :: OS Independent
Classifier: Programming Language :: Python
Classifier: Framework :: Django
Classifier: Natural Language :: English
Classifier: Natural Language :: French
Classifier: Topic :: Internet :: WWW/HTTP :: Dynamic Content
Classifier: Topic :: Internet :: WWW/HTTP :: WSGI :: Application
